rtl/alu.v
module alu(
    input [31:0]a,
    input [31:0]b,
    input [3:0]op,
    output reg[31:0]y
);
always @(*) begin
    

case (op)
 4'b0000 : y=a+b;
 4'b0001 : y=a-b;
 4'b0010 : y=a&b;
 4'b0011 : y=a|b;
 4'b0100 : y=a^b;
 4'b0101 : y=a<<b;
 4'b0110 : y=a>>b;
 4'b0111 : y=$signed(a)>>>b;
 4'b1000 : y= $signed(a)<$signed(b) ;
 4'b1001 : y=a<b;
 default: y=4'b0000;
endcase
end
endmodule

tb/alu_tb.v
module alu_tb;
reg [31:0]a;
reg [31:0]b;
reg [3:0]op;
wire [31:0]y;
reg[31:0]operation;
alu dut(
    .a(a),
    .b(b),
    .op(op),
    .y(y)
);

initial begin
    a=4'b0001;
    b=4'b0011;
    op=4'b0000;
    #10

    a=4'b1010;
    b=4'b0011;
    op=4'b0001;
    #10;


    a=4'b1010;
    b=4'b0011;
    op=4'b0010;
    #10;


    a=4'b1010;
    b=4'b0011;
    op=4'b0011;
    #10;


    a=4'b1111;
    b=4'b0000;
    op=4'b0100;
    #10;


    a = 4'b0011;
b = 4'b0001;
op = 4'b0101;
#10;


   a = 4'b0011;
b = 4'b0001;
op = 4'b0110;
#10;


  a = 32'b11111111111111111111111111111100;
b = 32'd1;
op = 4'b0111;
#10;

   a = 4'b1101;
b = 4'b0010;
op = 4'b1000;
#10;



  a = 4'b1101;
b = 4'b0010;
op = 4'b1001;
#10;

a = 32'd10;
b = 32'd20;
op = 4'b0000;
#10;

$finish;
end
always @(*) begin
      case(op)
     4'b0000: operation = "ADD";
    4'b0001: operation = "SUB";
    4'b0010: operation = "AND";
    4'b0011: operation = "OR";
    4'b0100: operation = "XOR";
    4'b0101: operation = "SLL";
    4'b0110: operation = "SRL";
    4'b0111: operation = "SRA";
    4'b1000: operation = "SLT";
    4'b1001: operation = "SLTU";
    default: operation = "UNKNOWN";
endcase
end
initial begin
    
    $dumpfile("alu.vcd");
    $dumpvars(0,alu_tb);
  
    $monitor("Time=%0t  |  A=%4b  |  B=%4b  |  Operation=%s |  Output=%4b",$time,a,b,operation,y);
end
endmodule

alu.vcd
$date
	Thu Sep 03 16:48:42 2026
$end
$version
	Icarus Verilog
$end
$timescale
	1s
$end
$scope module alu_tb $end
$var wire 32 ! y [31:0] $end
$var reg 32 " a [31:0] $end
$var reg 32 # b [31:0] $end
$var reg 4 $ op [3:0] $end
$var reg 32 % operation [31:0] $end
$scope module dut $end
$var wire 32 & a [31:0] $end
$var wire 32 ' b [31:0] $end
$var wire 4 ( op [3:0] $end
$var reg 32 ) y [31:0] $end
$upscope $end
$upscope $end
$enddefinitions $end
$comment Show the parameter values. $end
$dumpall
$end
#0
$dumpvars
b100 )
b0 (
b11 '
b1 &
b10000010100010001000100 %
b0 $
b11 #
b1 "
b100 !
$end
#10
b10100110101010101000010 %
b111 !
b111 )
b1 $
b1 (
b1010 "
b1010 &
#20
b10 !
b10 )
b10000010100111001000100 %
b10 $
b10 (
#30
b1011 !
b1011 )
b100111101010010 %
b11 $
b11 (
#40
b10110000100111101010010 %
b1111 !
b1111 )
b100 $
b100 (
b0 #
b0 '
b1111 "
b1111 &
#50
b10100110100110001001100 %
b110 !
b110 )
b101 $
b101 (
b1 #
b1 '
b11 "
b11 &
#60
b1 !
b1 )
b10100110101001001001100 %
b110 $
b110 (
#70
b10100110101001001000001 %
b11111111111111111111111111111110 !
b11111111111111111111111111111110 )
b111 $
b111 (
b11111111111111111111111111111100 "
b11111111111111111111111111111100 &
#80
b10100110100110001010100 %
b0 !
b0 )
b1000 $
b1000 (
b10 #
b10 '
b1101 "
b1101 &
#90
b1010011010011000101010001010101 %
b1001 $
b1001 (
#100
b10000010100010001000100 %
b11110 !
b11110 )
b0 $
b0 (
b10100 #
b10100 '
b1010 "
b1010 &
