rtl/branch_unit.v
module branch_unit (
    input  [31:0] rs1_value,
    input  [31:0] rs2_value,
    input  [31:0] pc,
    input  [31:0] immediate,

    input         branch,
    input         jump,

    input  [2:0]  func3,

    output reg        branch_taken,
    output reg [31:0] target_address
);

always @(*) begin

    branch_taken  = 1'b0;
    target_address = pc + immediate;

    // ---------------------------------------------------------
    // Conditional branches
    // ---------------------------------------------------------

    if (branch) begin

        case (func3)

            // BEQ
            3'b000: begin
                if (rs1_value == rs2_value)
                    branch_taken = 1'b1;
            end

            // BNE
            3'b001: begin
                if (rs1_value != rs2_value)
                    branch_taken = 1'b1;
            end

            // BLT
            3'b100: begin
                if ($signed(rs1_value) < $signed(rs2_value))
                    branch_taken = 1'b1;
            end

            // BGE
            3'b101: begin
                if ($signed(rs1_value) >= $signed(rs2_value))
                    branch_taken = 1'b1;
            end

            // BLTU
            3'b110: begin
                if (rs1_value < rs2_value)
                    branch_taken = 1'b1;
            end

            // BGEU
            3'b111: begin
                if (rs1_value >= rs2_value)
                    branch_taken = 1'b1;
            end

            default: begin
                branch_taken = 1'b0;
            end

        endcase

    end

    // ---------------------------------------------------------
    // Jumps
    // ---------------------------------------------------------

    if (jump) begin
        branch_taken = 1'b1;
        target_address = pc + immediate;
    end

end

endmodule

tb/branch_unit_tb.v
`timescale 1ns/1ps

module branch_unit_tb;

reg [31:0] rs1_value;
reg [31:0] rs2_value;
reg [31:0] pc;
reg [31:0] immediate;

reg branch;
reg jump;

reg [2:0] func3;

wire branch_taken;
wire [31:0] target_address;

branch_unit dut (
    .rs1_value(rs1_value),
    .rs2_value(rs2_value),
    .pc(pc),
    .immediate(immediate),

    .branch(branch),
    .jump(jump),

    .func3(func3),

    .branch_taken(branch_taken),
    .target_address(target_address)
);

initial begin

    pc = 32'd100;
    immediate = 32'd20;

    branch = 1'b0;
    jump = 1'b0;

    rs1_value = 32'd10;
    rs2_value = 32'd10;

    func3 = 3'b000;

    // ------------------------------------------------
    // Test 1: BEQ - taken
    // ------------------------------------------------

    branch = 1'b1;
    func3 = 3'b000;

    #10;


    // ------------------------------------------------
    // Test 2: BEQ - not taken
    // ------------------------------------------------

    rs2_value = 32'd20;

    #10;


    // ------------------------------------------------
    // Test 3: BNE - taken
    // ------------------------------------------------

    func3 = 3'b001;

    #10;


    // ------------------------------------------------
    // Test 4: BNE - not taken
    // ------------------------------------------------

    rs2_value = 32'd10;

    #10;


    // ------------------------------------------------
    // Test 5: BLT - taken
    // ------------------------------------------------

    rs1_value = 32'd5;
    rs2_value = 32'd10;
    func3 = 3'b100;

    #10;


    // ------------------------------------------------
    // Test 6: BGE - taken
    // ------------------------------------------------

    rs1_value = 32'd10;
    rs2_value = 32'd5;
    func3 = 3'b101;

    #10;


    // ------------------------------------------------
    // Test 7: BLTU - taken
    // ------------------------------------------------

    rs1_value = 32'd5;
    rs2_value = 32'd10;
    func3 = 3'b110;

    #10;


    // ------------------------------------------------
    // Test 8: BGEU - taken
    // ------------------------------------------------

    rs1_value = 32'd10;
    rs2_value = 32'd5;
    func3 = 3'b111;

    #10;


    // ------------------------------------------------
    // Test 9: JAL
    // ------------------------------------------------

    branch = 1'b0;
    jump = 1'b1;

    pc = 32'd200;
    immediate = 32'd40;

    #10;


    // ------------------------------------------------
    // Test 10: No branch / jump
    // ------------------------------------------------

    jump = 1'b0;

    #10;

    $finish;

end

initial begin

    $monitor(
        "Time=%0t | PC=%d | RS1=%d | RS2=%d | Imm=%d | Branch=%b | Jump=%b | Func3=%b | Taken=%b | Target=%d",
        $time,
        pc,
        rs1_value,
        rs2_value,
        immediate,
        branch,
        jump,
        func3,
        branch_taken,
        target_address
    );

end

initial begin

    $dumpfile("branch_unit.vcd");
    $dumpvars(0, branch_unit_tb);

end

endmodule

branch_unit.vcd
$date
	Fri Sep 11 12:19:00 2026
$end
$version
	Icarus Verilog
$end
$timescale
	1ps
$end
$scope module branch_unit_tb $end
$var wire 32 ! target_address [31:0] $end
$var wire 1 " branch_taken $end
$var reg 1 # branch $end
$var reg 3 $ func3 [2:0] $end
$var reg 32 % immediate [31:0] $end
$var reg 1 & jump $end
$var reg 32 ' pc [31:0] $end
$var reg 32 ( rs1_value [31:0] $end
$var reg 32 ) rs2_value [31:0] $end
$scope module dut $end
$var wire 1 # branch $end
$var wire 3 * func3 [2:0] $end
$var wire 32 + immediate [31:0] $end
$var wire 1 & jump $end
$var wire 32 , pc [31:0] $end
$var wire 32 - rs1_value [31:0] $end
$var wire 32 . rs2_value [31:0] $end
$var reg 1 " branch_taken $end
$var reg 32 / target_address [31:0] $end
$upscope $end
$upscope $end
$enddefinitions $end
$comment Show the parameter values. $end
$dumpall
$end
#0
$dumpvars
b1111000 /
b1010 .
b1010 -
b1100100 ,
b10100 +
b0 *
b1010 )
b1010 (
b1100100 '
0&
b10100 %
b0 $
1#
1"
b1111000 !
$end
#10000
0"
b10100 )
b10100 .
#20000
1"
b1 $
b1 *
#30000
0"
b1010 )
b1010 .
#40000
1"
b100 $
b100 *
b101 (
b101 -
#50000
1"
b101 $
b101 *
b101 )
b101 .
b1010 (
b1010 -
#60000
1"
b110 $
b110 *
b1010 )
b1010 .
b101 (
b101 -
#70000
1"
b111 $
b111 *
b101 )
b101 .
b1010 (
b1010 -
#80000
b11110000 !
b11110000 /
1"
b101000 %
b101000 +
b11001000 '
b11001000 ,
1&
0#
#90000
0"
0&
