rtl/d_flipflop.v
module d_flipflop(
    input d,
    input clk,
    output reg q
);

always @(posedge clk) begin
    q<=d;
    
end
endmodule

tb/d_flipflop_tb.v
module d_flipflop_tb;
    reg d;
    reg clk;
    wire q;
    
    d_flipflop dut(
        .d(d),
        .clk(clk),
        .q(q)
    );
    
    initial begin
        clk=0;
        forever #5 clk=~clk;
    end
    initial begin 
        d=0;
        #7 d=1;
        #10 d=0;
        #12 d=1;
        #15 d=1;
        #20 d=0;
        $finish;
    end
    initial begin
        $dumpfile("d_flipflop.vcd");
        $dumpvars(0,d_flipflop_tb);
        $monitor("Time =%t  |  clk=%b  |  d=%b  |  q=%b",$time,clk,d,q);
    
    end
endmodule

d_flipflop.vcd
$date
	Thu Sep 03 09:33:21 2026
$end
$version
	Icarus Verilog
$end
$timescale
	1s
$end
$scope module d_flipflop_tb $end
$var wire 1 ! q $end
$var reg 1 " clk $end
$var reg 1 # d $end
$scope module dut $end
$var wire 1 " clk $end
$var wire 1 # d $end
$var reg 1 ! q $end
$upscope $end
$upscope $end
$enddefinitions $end
$comment Show the parameter values. $end
$dumpall
$end
#0
$dumpvars
0#
0"
x!
$end
#5
0!
1"
#7
1#
#10
0"
#15
1!
1"
#17
0#
#20
0"
#25
0!
1"
#29
1#
#30
0"
#35
1!
1"
#40
0"
#45
1"
#50
0"
#55
1"
#60
0"
#64
0#
