rtl/register4.v
module register4(
    input [3:0]d,
    input clk,
    output reg[3:0]q
);
always @(posedge clk) begin
    q<=d;
end
endmodule

tb/register4_tb.v
module register4_tb;
reg [3:0]d;
reg clk;
wire [3:0]q;

register4 dut(
    .d(d),
    .clk(clk),
    .q(q)
);
initial begin
    clk=0;
    forever #5 clk =~clk;
end
initial begin
    d=4'b0000;
    #7 d=4'b1001;
    #10 d=4'b1101;
    #15 d=4'b1110;
    #20 d=4'b1111;
    $finish;
end
initial begin
    $dumpfile("register4.vcd");
    $dumpvars(0,register4_tb);
    $monitor("Time=%0t  |  clk=%b  |  d=%4b  |  q=%4b",$time,clk,d,q);
end
endmodule

register4.vcd
$date
	Thu Sep 03 12:41:21 2026
$end
$version
	Icarus Verilog
$end
$timescale
	1s
$end
$scope module register4_tb $end
$var wire 4 ! q [3:0] $end
$var reg 1 " clk $end
$var reg 4 # d [3:0] $end
$scope module dut $end
$var wire 1 " clk $end
$var wire 4 $ d [3:0] $end
$var reg 4 % q [3:0] $end
$upscope $end
$upscope $end
$enddefinitions $end
$comment Show the parameter values. $end
$dumpall
$end
#0
$dumpvars
bx %
b0 $
b0 #
0"
bx !
$end
#5
b0 !
b0 %
1"
#7
b1001 #
b1001 $
#10
0"
#15
b1001 !
b1001 %
1"
#17
b1101 #
b1101 $
#20
0"
#25
b1101 !
b1101 %
1"
#30
0"
#32
b1110 #
b1110 $
#35
b1110 !
b1110 %
1"
#40
0"
#45
1"
#50
0"
#52
b1111 #
b1111 $
